nirum_http.py
nirum_http-0.1.1.dist-info/DESCRIPTION.rst
nirum_http-0.1.1.dist-info/METADATA
nirum_http-0.1.1.dist-info/RECORD
nirum_http-0.1.1.dist-info/WHEEL
nirum_http-0.1.1.dist-info/metadata.json
nirum_http-0.1.1.dist-info/top_level.txt
