Metadata-Version: 2.0
Name: nirum-http
Version: 0.1.1
Summary: Nirum HTTP transport for Python
Home-page: https://github.com/spoqa/nirum-python-http
Author: Kang Hyojun
Author-email: iam.kanghyojun@gmail.com
License: MIT license
Platform: UNKNOWN
Requires-Dist: nirum (>=0.6.0)
Requires-Dist: requests (>=2.11.1)
Requires-Dist: six
Requires-Dist: typing; python_version<'3.5'
Provides-Extra: tests
Requires-Dist: flake8-import-order (<1.0,>=0.12); extra == 'tests'
Requires-Dist: flake8-import-order-spoqa (<2.0.0,>=1.0.0); extra == 'tests'
Requires-Dist: pytest (<4.0.0,>=3.1.2); extra == 'tests'
Requires-Dist: pytest-flake8 (>=0.8.1,<1.0.0); extra == 'tests'
Requires-Dist: requests-mock (>=1.3.0,<1.4.0); extra == 'tests'
